datakitpy/__init__.py
datakitpy/datakit.py
datakitpy/helpers.py
datakitpy/py.typed
datakitpy/resources.py
datakitpy-0.2.1.dist-info/LICENSE
datakitpy-0.2.1.dist-info/METADATA
datakitpy-0.2.1.dist-info/WHEEL
datakitpy-0.2.1.dist-info/top_level.txt
datakitpy-0.2.1.dist-info/RECORD
